LICENSE.interpreter
README.txt
setup.py
MochiInterpreter.egg-info/PKG-INFO
MochiInterpreter.egg-info/SOURCES.txt
MochiInterpreter.egg-info/dependency_links.txt
MochiInterpreter.egg-info/entry_points.txt
MochiInterpreter.egg-info/not-zip-safe
MochiInterpreter.egg-info/paster_plugins.txt
MochiInterpreter.egg-info/requires.txt
MochiInterpreter.egg-info/sqlobject.txt
MochiInterpreter.egg-info/top_level.txt
mochiinterpreter/__init__.py
mochiinterpreter/release.py
mochiinterpreter/widgets.py
mochiinterpreter/static/css/interpreter.css
mochiinterpreter/static/images/favicon.ico
mochiinterpreter/static/images/tg_under_the_hood.png
mochiinterpreter/static/javascript/interpreter.js
mochiinterpreter/templates/__init__.py
