Metadata-Version: 1.0
Name: MochiInterpreter
Version: 1.3.1
Summary: This widget is an implementation of the interpreter example from MochiKit
